main.py
setup.py
MVDream_threestudio.egg-info/PKG-INFO
MVDream_threestudio.egg-info/SOURCES.txt
MVDream_threestudio.egg-info/dependency_links.txt
MVDream_threestudio.egg-info/requires.txt
MVDream_threestudio.egg-info/top_level.txt